jadapy/ComplexEpetraInterface.py
jadapy/EpetraInterface.py
jadapy/NumPyInterface.py
jadapy/Target.py
jadapy/__init__.py
jadapy/correction_equation.py
jadapy/generalized_schur.py
jadapy/jdqr.py
jadapy/jdqz.py
jadapy/orthogonalization.py
jadapy/schur.py
jadapy/utils.py
jadapy-1.0.0.dist-info/LICENSE
jadapy-1.0.0.dist-info/METADATA
jadapy-1.0.0.dist-info/WHEEL
jadapy-1.0.0.dist-info/top_level.txt
jadapy-1.0.0.dist-info/RECORD
