Metadata-Version: 2.1
Name: jadapy
Version: 1.0.0
Summary: Implementations of JDQR and JDQZ with optional integration with Trilinos.
Home-page: https://github.com/BIMAU/jadapy
Author: Sven Baars
Author-email: s.baars@rug.nl
License: Apache License 2.0
Classifier: Development Status :: 5 - Production/Stable
Classifier: Environment :: Console
Classifier: Intended Audience :: Developers
Classifier: Intended Audience :: Science/Research
Classifier: License :: OSI Approved :: Apache Software License
Classifier: Operating System :: OS Independent
Classifier: Programming Language :: Python
Classifier: Topic :: Scientific/Engineering
License-File: LICENSE
Requires-Dist: numpy
Requires-Dist: scipy>=1.10
Provides-Extra: all
Requires-Dist: pytest; extra == "all"
Provides-Extra: test
Requires-Dist: pytest; extra == "test"
